twisted/__init__.py
twisted/__main__.py
twisted/_version.py
twisted/copyright.py
twisted/plugin.py
twisted/py.typed
twisted/_threads/__init__.py
twisted/_threads/_convenience.py
twisted/_threads/_ithreads.py
twisted/_threads/_memory.py
twisted/_threads/_pool.py
twisted/_threads/_team.py
twisted/_threads/_threadworker.py
twisted/application/__init__.py
twisted/application/_client_service.py
twisted/application/app.py
twisted/application/internet.py
twisted/application/reactors.py
twisted/application/service.py
twisted/application/strports.py
twisted/application/newsfragments/10146.misc
twisted/application/newsfragments/9746.misc
twisted/application/runner/__init__.py
twisted/application/runner/_exit.py
twisted/application/runner/_pidfile.py
twisted/application/runner/_runner.py
twisted/application/twist/__init__.py
twisted/application/twist/_options.py
twisted/application/twist/_twist.py
twisted/cred/__init__.py
twisted/cred/_digest.py
twisted/cred/checkers.py
twisted/cred/credentials.py
twisted/cred/error.py
twisted/cred/portal.py
twisted/cred/strcred.py
twisted/enterprise/__init__.py
twisted/enterprise/adbapi.py
twisted/internet/__init__.py
twisted/internet/_baseprocess.py
twisted/internet/_deprecate.py
twisted/internet/_dumbwin32proc.py
twisted/internet/_glibbase.py
twisted/internet/_idna.py
twisted/internet/_multicast.py
twisted/internet/_newtls.py
twisted/internet/_pollingfile.py
twisted/internet/_posixserialport.py
twisted/internet/_posixstdio.py
twisted/internet/_producer_helpers.py
twisted/internet/_resolver.py
twisted/internet/_signals.py
twisted/internet/_sslverify.py
twisted/internet/_threadedselect.py
twisted/internet/_win32serialport.py
twisted/internet/_win32stdio.py
twisted/internet/abstract.py
twisted/internet/address.py
twisted/internet/asyncioreactor.py
twisted/internet/base.py
twisted/internet/cfreactor.py
twisted/internet/default.py
twisted/internet/defer.py
twisted/internet/endpoints.py
twisted/internet/epollreactor.py
twisted/internet/error.py
localstack_twisted-25.5.0.dist-info/METADATA
localstack_twisted-25.5.0.dist-info/WHEEL
localstack_twisted-25.5.0.dist-info/RECORD
